{
	"format_version": "1.12.0",
	"minecraft:geometry": [
		{
			"description": {
				"identifier": "geometry.unknown",
				"texture_width": 164,
				"texture_height": 132,
				"visible_bounds_width": 6,
				"visible_bounds_height": 4,
				"visible_bounds_offset": [0, 1, 0]
			},
			"bones": [
				{
					"name": "root",
					"pivot": [0, 24, 0]
				},
				{
					"name": "Body",
					"parent": "root",
					"pivot": [0, 24, 0],
					"cubes": [
						{"origin": [-6, 18, 0], "size": [12, 12, 18], "uv": [0, 0]}
					]
				},
				{
					"name": "Caudal",
					"parent": "Body",
					"pivot": [0, 24, 17],
					"rotation": [0, 0.90561, 0],
					"cubes": [
						{"origin": [-3, 20, 17], "size": [6, 8, 9], "uv": [0, 32]}
					]
				},
				{
					"name": "Caudal_fin",
					"parent": "Caudal",
					"pivot": [0, 24, 25],
					"cubes": [
						{"origin": [0, 19, 25], "size": [0, 10, 14], "uv": [0, 36]}
					]
				},
				{
					"name": "Adipose_fin",
					"parent": "Caudal",
					"pivot": [0, 28, 21.5],
					"cubes": [
						{"origin": [0, 28, 21], "size": [0, 4, 7], "uv": [32, 34]}
					]
				},
				{
					"name": "Anal_fin",
					"parent": "Caudal",
					"pivot": [0, 21, 24.5],
					"cubes": [
						{"origin": [0, 18, 24], "size": [0, 3, 4], "uv": [62, 28]}
					]
				},
				{
					"name": "Head",
					"parent": "Body",
					"pivot": [0, 25, 0],
					"cubes": [
						{"origin": [-3.5, 21.5, -10], "size": [7, 7, 11], "uv": [61, 0]}
					]
				},
				{
					"name": "Crown",
					"parent": "Head",
					"pivot": [0, 27.5, 1],
					"cubes": [
						{"origin": [0, 27.5, -13], "size": [0, 11, 13], "uv": [61, 7]}
					]
				},
				{
					"name": "Upper_jaw_teeth_1",
					"parent": "Head",
					"pivot": [-2.5, 22, -5],
					"cubes": [
						{"origin": [-3, 20, -10], "size": [1, 2, 11], "uv": [61, 40]}
					]
				},
				{
					"name": "Upper_jaw_teeth_2",
					"parent": "Head",
					"pivot": [2.5, 22, -5],
					"cubes": [
						{"origin": [2, 20, -10], "size": [1, 2, 11], "uv": [61, 40]}
					]
				},
				{
					"name": "Upper_jaw_teeth_3",
					"parent": "Head",
					"pivot": [0, 21.5, -9],
					"cubes": [
						{"origin": [-2.5, 19.5, -9.5], "size": [5, 2, 1], "uv": [61, 54]}
					]
				},
				{
					"name": "Lower_jaw",
					"parent": "Body",
					"pivot": [0, 20.5, 1],
					"cubes": [
						{"origin": [-3.5, 19.5, -10], "size": [7, 2, 12], "uv": [98, 4]}
					]
				},
				{
					"name": "Barbel",
					"parent": "Lower_jaw",
					"pivot": [0, 20.5, -9.5],
					"cubes": [
						{"origin": [-0.5, -16.5, -10], "size": [1, 37, 1], "uv": [0, 62]}
					]
				},
				{
					"name": "Lure",
					"parent": "Barbel",
					"pivot": [0, -14.5, -9.5],
					"cubes": [
						{"origin": [-1.5, -18.5, -11], "size": [3, 4, 3], "uv": [0, 102]}
					]
				},
				{
					"name": "Lure_barbel",
					"parent": "Lure",
					"pivot": [0, -18.5, -9.5],
					"cubes": [
						{"origin": [0, -21.5, -11], "size": [0, 3, 3], "uv": [0, 108]}
					]
				},
				{
					"name": "Barbel_photophores_1",
					"parent": "Barbel",
					"pivot": [0, 20.5, -9.5],
					"cubes": [
						{"origin": [0, -14.5, -13], "size": [0, 35, 7], "uv": [6, 56]}
					]
				},
				{
					"name": "Barbel_photophores_2",
					"parent": "Barbel",
					"pivot": [0, 20.5, -9.5],
					"cubes": [
						{"origin": [-3.5, -14.5, -9.5], "size": [7, 35, 0], "uv": [23, 64]}
					]
				},
				{
					"name": "Lower_jaw_teeth_1",
					"parent": "Lower_jaw",
					"pivot": [-2.9, 21.5, -5],
					"cubes": [
						{"origin": [-3.4, 21.5, -10], "size": [1, 3, 11], "uv": [98, 20]}
					]
				},
				{
					"name": "Lower_jaw_teeth_2",
					"parent": "Lower_jaw",
					"pivot": [2.9, 21.5, -5],
					"cubes": [
						{"origin": [2.4, 21.5, -10], "size": [1, 3, 11], "uv": [98, 20]}
					]
				},
				{
					"name": "Lower_jaw_teeth_3",
					"parent": "Lower_jaw",
					"pivot": [0, 21.5, -9.9],
					"cubes": [
						{"origin": [-2.5, 21.5, -9.9], "size": [5, 3, 1], "uv": [98, 36]}
					]
				},
				{
					"name": "Dorsal_fin",
					"parent": "Body",
					"pivot": [0, 30, 0.5],
					"cubes": [
						{"origin": [0, 30, 0], "size": [0, 7, 16], "uv": [29, 16]}
					]
				},
				{
					"name": "Pectoral_fin_1",
					"parent": "Body",
					"pivot": [-6, 18, 0.5],
					"rotation": [0, 0, 28.7],
					"cubes": [
						{"origin": [-6, 10, 0], "size": [0, 8, 7], "uv": [0, 2]}
					]
				},
				{
					"name": "Pectoral_fin_2",
					"parent": "Body",
					"pivot": [6, 18, 0.5],
					"rotation": [0, 0, -28.7],
					"cubes": [
						{"origin": [6, 10, 0], "size": [0, 8, 7], "uv": [0, 2]}
					]
				},
				{
					"name": "Pelvic_fin_1",
					"parent": "Body",
					"pivot": [-5.9, 19, 14.5],
					"rotation": [0, 0, 5.22],
					"cubes": [
						{"origin": [-5.9, 13, 14], "size": [0, 6, 8], "uv": [44, 3]}
					]
				},
				{
					"name": "Pelvic_fin_2",
					"parent": "Body",
					"pivot": [5.9, 19, 14.5],
					"rotation": [0, 0, -5.22],
					"cubes": [
						{"origin": [5.9, 13, 14], "size": [0, 6, 8], "uv": [44, 3]}
					]
				}
			]
		}
	]
}