{
  "type": "features:generic",
  "pools": [
    {
      "type": "features:pool",
      "pool": "deep_trenches:trees/fuchsitra/small_crowns",
      "properties": {
        "type": "features:properties",
        "rotations": [ "clockwise_90", "none" ]
      },
      "context": {
        "type": "features:tree",
        "overrides": [
          {
            "type": "features:parameter",
            "parameter": "features:height",
            "from": [
              {
                "type": "features:ranged",
                "range": {
                  "min": 10,
                  "max": 15
                }
              }
            ]
          }
        ]
      },
      "entries": [
        {
          "type": "features:entry",
          "structure": "deep_trenches:trees/fuchsitra/crown/small_crown_01",
          "functions": [
            {
              "function": "features:pivot",
              "offset": {
                "north": 1,
                "west": 4
              }
            }
          ]
        }
      ]
    }
  ]
}